bullet_safety_gym/__init__.py
bullet_safety_gym/envs/__init__.py
bullet_safety_gym/envs/agents.py
bullet_safety_gym/envs/bases.py
bullet_safety_gym/envs/builder.py
bullet_safety_gym/envs/env_utils.py
bullet_safety_gym/envs/obstacles.py
bullet_safety_gym/envs/sensors.py
bullet_safety_gym/envs/tasks.py
bullet_safety_gym/envs/worlds.py
bullet_safety_gym/envs/data/obstacles/apple.urdf
bullet_safety_gym/envs/data/obstacles/bomb.urdf
bullet_safety_gym/envs/data/obstacles/box.urdf
bullet_safety_gym/envs/data/obstacles/checker_huge.gif
bullet_safety_gym/envs/data/obstacles/circle_zone.urdf
bullet_safety_gym/envs/data/obstacles/goal_zone.urdf
bullet_safety_gym/envs/data/obstacles/line_boundary.urdf
bullet_safety_gym/envs/data/obstacles/octagon_wall.urdf
bullet_safety_gym/envs/data/obstacles/orb.urdf
bullet_safety_gym/envs/data/obstacles/pillar.urdf
bullet_safety_gym/envs/data/obstacles/puck.STL
bullet_safety_gym/envs/data/obstacles/puck.mtl
bullet_safety_gym/envs/data/obstacles/puck.obj
bullet_safety_gym/envs/data/obstacles/puck.urdf
bullet_safety_gym/envs/data/obstacles/puddle.urdf
bullet_safety_gym/envs/data/obstacles/room_20x20.urdf
bullet_safety_gym/envs/data/obstacles/room_30x30.urdf
bullet_safety_gym/envs/data/obstacles/room_40x40.urdf
bullet_safety_gym/envs/data/obstacles/sphere.urdf
bullet_safety_gym/envs/data/obstacles/sphere2.urdf
bullet_safety_gym/envs/data/obstacles/textured_sphere_smooth.mtl
bullet_safety_gym/envs/data/obstacles/textured_sphere_smooth.obj
bullet_safety_gym/envs/data/plane/checker_blue.png
bullet_safety_gym/envs/data/plane/plane.mtl
bullet_safety_gym/envs/data/plane/plane10.obj
bullet_safety_gym/envs/data/plane/plane10.urdf
bullet_safety_gym/envs/data/plane/plane100.obj
bullet_safety_gym/envs/data/plane/plane100.urdf
bullet_safety_gym/envs/data/plane/plane15.obj
bullet_safety_gym/envs/data/plane/plane15.urdf
bullet_safety_gym/envs/data/plane/plane20.obj
bullet_safety_gym/envs/data/plane/plane20.urdf
bullet_safety_gym/envs/data/plane/plane250.obj
bullet_safety_gym-1.4.0.dist-info/LICENSE
bullet_safety_gym-1.4.0.dist-info/METADATA
bullet_safety_gym-1.4.0.dist-info/WHEEL
bullet_safety_gym-1.4.0.dist-info/top_level.txt
bullet_safety_gym-1.4.0.dist-info/RECORD
