Metadata-Version: 2.1
Name: bullet-safety-gym
Version: 1.4.0
Summary: A framework to benchmark safety in Reinforcement Learning.
Home-page: https://github.com/liuzuxin/Bullet-Safety-Gym
Author: bullet-safety-gym-contributors
Author-email: zuxin1997@gmail.com
License: MIT license
Platform: Linux Ubuntu
Platform: darwin
Classifier: Development Status :: 3 - Alpha
Classifier: Intended Audience :: Science/Research
Classifier: Topic :: Scientific/Engineering :: Artificial Intelligence
Classifier: Topic :: Software Development :: Libraries :: Python Modules
Classifier: License :: OSI Approved :: MIT License
Classifier: Programming Language :: Python :: 3.8
Classifier: Programming Language :: Python :: 3.9
Classifier: Programming Language :: Python :: 3.10
Requires-Python: >=3.8
License-File: LICENSE
Requires-Dist: gymnasium (~=0.28.1)
Requires-Dist: numpy (>1.16.0)
Requires-Dist: pybullet (>=3.0.6)
Provides-Extra: dev
Requires-Dist: sphinx ; extra == 'dev'
Requires-Dist: sphinx-rtd-theme ; extra == 'dev'
Requires-Dist: jinja2 ; extra == 'dev'
Requires-Dist: sphinxcontrib-bibtex ; extra == 'dev'
Requires-Dist: flake8 ; extra == 'dev'
Requires-Dist: flake8-bugbear ; extra == 'dev'
Requires-Dist: yapf ; extra == 'dev'
Requires-Dist: isort ; extra == 'dev'
Requires-Dist: pytest ; extra == 'dev'
Requires-Dist: pytest-cov ; extra == 'dev'
Requires-Dist: networkx ; extra == 'dev'
Requires-Dist: mypy ; extra == 'dev'
Requires-Dist: pydocstyle ; extra == 'dev'
Requires-Dist: doc8 ; extra == 'dev'
Requires-Dist: pillow ; extra == 'dev'
Requires-Dist: shimmy ; extra == 'dev'
Requires-Dist: pre-commit ; extra == 'dev'
